libvis/VisVars.py
libvis/VisWorker.py
libvis/__about__.py
libvis/__init__.py
libvis/http_server.py
libvis/interface.py
libvis/main.py
libvis/front_build/index.bundle.js
libvis/front_build/index.html
libvis/helpers/AttrDict.py
libvis/helpers/__init__.py
libvis/helpers/threaded.py
libvis/modules/Base.py
libvis/modules/__init__.py
libvis/modules/installed/__init__.py
libvis/modules/installed/Gallery/__init__.py
libvis/modules/installed/Gallery/main.py
libvis/modules/installed/Image/__init__.py
libvis/modules/installed/Image/main.py
libvis/modules/installed/WebPage/__init__.py
libvis/modules/installed/WebPage/back.py
libvis/modules/installed/uicontrols/__init__.py
libvis/modules/installed/uicontrols/uicontrols.py
libvis/modules/installed/uicontrols/utils.py
libvis/websocket/__init__.py
libvis/websocket/message_gen.py
libvis/websocket/test_ws_server.py
libvis/websocket/ws_client.py
libvis/websocket/ws_server.py
libvis-0.1.3.data/data/index.bundle.js
libvis-0.1.3.data/data/index.html
libvis-0.1.3.dist-info/METADATA
libvis-0.1.3.dist-info/WHEEL
libvis-0.1.3.dist-info/top_level.txt
libvis-0.1.3.dist-info/RECORD
