Metadata-Version: 2.1
Name: libvis
Version: 0.1.3
Summary: Interactive live object visualization for python
Home-page: https://github.com/libvis/python-libvis
Author: Dan Lykov
Author-email: lkvdan@gmail.com
License: GPLv2
Keywords: tools,data,framework,visualization
Platform: UNKNOWN
Requires-Python: >=3.3
Requires-Dist: legimens
Requires-Dist: matplotlib
Requires-Dist: numpy
Requires-Dist: requests
Requires-Dist: trio (>=0.13)
Requires-Dist: trio-websocket (>=0.8)
